deephaven/python_remote_file_source/__init__.py
deephaven/python_remote_file_source/json_rpc.py
deephaven/python_remote_file_source/message_stream.py
deephaven/python_remote_file_source/module_loader.py
deephaven/python_remote_file_source/plugin_object.py
deephaven/python_remote_file_source/plugin_type.py
deephaven/python_remote_file_source/register.py
deephaven/python_remote_file_source/types.py
deephaven/python_remote_file_source/_js/package.json
deephaven/python_remote_file_source/_js/dist/index.js
deephaven_plugin_python_remote_file_source-0.1.2.dist-info/licenses/LICENSE
deephaven_plugin_python_remote_file_source-0.1.2.dist-info/METADATA
deephaven_plugin_python_remote_file_source-0.1.2.dist-info/WHEEL
deephaven_plugin_python_remote_file_source-0.1.2.dist-info/entry_points.txt
deephaven_plugin_python_remote_file_source-0.1.2.dist-info/top_level.txt
deephaven_plugin_python_remote_file_source-0.1.2.dist-info/RECORD
