Metadata-Version: 2.4
Name: deephaven-plugin-python-remote-file-source
Version: 0.1.2
Summary: A Deephaven bi-directional plugin to allow sourcing Python imports from a remote file source.
Home-page: https://github.com/deephaven/deephaven-plugins
Author: Deephaven Data Labs
Author-email: support@deephaven.io
Project-URL: Source Code, https://github.com/deephaven/deephaven-plugins
Project-URL: Bug Tracker, https://github.com/deephaven/deephaven-plugins/issues
Keywords: deephaven,plugin
Platform: any
Classifier: Programming Language :: Python :: 3
Classifier: License :: OSI Approved :: Apache Software License
Classifier: Operating System :: OS Independent
Classifier: Environment :: Plugins
Classifier: Topic :: Scientific/Engineering :: Visualization
Classifier: Development Status :: 3 - Alpha
License-File: LICENSE
Requires-Dist: deephaven-core>=0.35.1
Requires-Dist: deephaven-plugin>=0.6.0
Requires-Dist: deephaven-plugin-utilities
Dynamic: license-file
